stairwell/__init__.py
stairwell_openapi_client/py.typed
stairwell-0.0.4.dist-info/LICENSE
stairwell-0.0.4.dist-info/METADATA
stairwell-0.0.4.dist-info/WHEEL
stairwell-0.0.4.dist-info/RECORD
