Metadata-Version: 2.1
Name: stairwell
Version: 0.0.4
Summary: A Python client for the Stairwell platform.
Home-page: https://stairwell.com/
License: Apache 2.0
Keywords: OpenAPI,OpenAPI-Generator,Stairwell V1 HTTP APIs
Author: Andrew Liu
Author-email: liu@stairwell.com
Requires-Python: >=3.8,<4.0
Classifier: License :: Other/Proprietary License
Classifier: Programming Language :: Python :: 3
Classifier: Programming Language :: Python :: 3.8
Classifier: Programming Language :: Python :: 3.9
Classifier: Programming Language :: Python :: 3.10
Classifier: Programming Language :: Python :: 3.11
Classifier: Programming Language :: Python :: 3.12
Requires-Dist: aenum (>=3.1.11)
Requires-Dist: aiohttp (>=3.8.4)
Requires-Dist: pydantic (>=1.10.5,<2.0.0)
Requires-Dist: python-dateutil (>=2.8.2)
Requires-Dist: urllib3 (>=1.25.3)
Project-URL: Documentation, https://docs.stairwell.com/
Project-URL: Repository, https://github.com/stairwell-inc/stairwell-python
